pyjuhelpers/__init__.py
pyjuhelpers/basicconfig.py
pyjuhelpers/logging.py
pyjuhelpers/module_import.py
pyjuhelpers/progress_bar.py
pyjuhelpers/string_format.py
pyjuhelpers/timer.py
pyjuhelpers-0.3.dist-info/METADATA
pyjuhelpers-0.3.dist-info/RECORD
pyjuhelpers-0.3.dist-info/WHEEL
pyjuhelpers-0.3.dist-info/entry_points.txt
pyjuhelpers-0.3.dist-info/top_level.txt
