Metadata-Version: 2.1
Name: pyjuhelpers
Version: 0.3
Summary: Add a short description here!
Home-page: http://...
Author: jumbrich
Author-email: jueumb@gmail.com
License: mit
Platform: any
Classifier: Development Status :: 4 - Beta
Classifier: Programming Language :: Python
Requires-Dist: pyyaml
Requires-Dist: structlog
